easyDataset/__init__.py
easyDataset-0.0.0.dist-info/LICENSE
easyDataset-0.0.0.dist-info/METADATA
easyDataset-0.0.0.dist-info/WHEEL
easyDataset-0.0.0.dist-info/top_level.txt
easyDataset-0.0.0.dist-info/RECORD
